Memoria de Datos/DM.v
module DM(
    input clk,
    input [4:0] addresDM,       // Direccion escritura
    input [31:0] wd,            // Dato para escritura
    input we,                   // Habilitacion de escritura
    output wire [31:0] rd       // Dato para Lectura

);
reg [31:0] Memoria_de_Datos [31:0];

//Bloque secuencial para actualizar el registro
always @(posedge clk) begin
    if (we) begin
            Memoria_de_Datos [addresDM]<= wd;
    end
end

assign rd = Memoria_de_Datos[addresDM];
endmodule

Memoria de Datos/DM_tb.v
`default_nettype none
`define DUMPSTR(x) `"x.vcd`"
`timescale 100 ns / 10 ns

module DM_tb();

parameter DURATION = 10;

reg clk = 0;
always #0.5 clk = ~clk;

reg [4:0] addresDM_tb;   // Dirección escritura
reg [31:0] wd_tb;        // Dato para escritura
reg we_tb;               // Habilitación de escritura
wire [31:0] rd_tb;       // Dato para Lectura

DM UUT (
    .clk(clk),
    .addresDM(addresDM_tb),
    .wd(wd_tb),
    .we(we_tb),
    .rd(rd_tb)
);



initial begin

    $dumpfile(`DUMPSTR(`VCD_OUTPUT));
    $dumpvars(0, DM_tb);
    
    // Inicialización
    we_tb = 0; // Inhabilitar escritura inicialmente
    wd_tb = 32'h00000000; // Inicializar dato de escritura

    // Escritura en la dirección 0
    addresDM_tb = 5'b00000; // Dirección de escritura
    wd_tb = 32'hA5A5A5A5; // Dato a escribir
    we_tb = 1; // Habilitar escritura
    #1; // Esperar un ciclo de reloj

    // Leer la dirección 0
    addresDM_tb = 5'b00000; // Dirección de lectura
    we_tb = 0;
    wd_tb = 32'hFFFF0FFF; // Dato a escribir
    #1; // Esperar un ciclo de reloj
    

    // Escritura en la dirección 1
    addresDM_tb = 5'b00001; // Dirección de escritura
    wd_tb = 32'hDEADBEEF; // Dato a escribir
    we_tb = 1; // Habilitar escritura
    #1; // Esperar un ciclo de reloj

    // Leer la dirección 1
    addresDM_tb = 5'b00001; // Dirección de lectura
    #1; // Esperar un ciclo de reloj
    
    // Escritura en la dirección 2
    addresDM_tb = 5'b00010; // Dirección de escritura
    wd_tb = 32'hFFFFFFFF; // Dato a escribir
    we_tb = 1; // Habilitar escritura
    #1; // Esperar un ciclo de reloj
    
    // Leer la dirección 2
    addresDM_tb = 5'b00010; // Dirección de lectura
    #1; // Esperar un ciclo de reloj
    
    // Escritura en la dirección 3
    addresDM_tb = 5'b00011; // Dirección de escritura
    wd_tb = 32'h12345678; // Dato a escribir
    we_tb = 1; // Habilitar escritura
    #1; // Esperar un ciclo de reloj
    
    // Leer la dirección 3
    addresDM_tb = 5'b00011; // Dirección de lectura
    #1; // Esperar un ciclo de reloj

    // 
    #(DURATION) $display("End of simulation");
    $finish;
end

endmodule

Memoria de Datos/DM_tb.vcd
$date
	Thu Oct 31 17:39:28 2024
$end
$version
	Icarus Verilog
$end
$timescale
	1ps
$end
$scope module DM_tb $end
$var wire 32 ! rd_tb [31:0] $end
$var parameter 32 " DURATION $end
$var reg 5 # addresDM_tb [4:0] $end
$var reg 1 $ clk $end
$var reg 32 % wd_tb [31:0] $end
$var reg 1 & we_tb $end
$scope module UUT $end
$var wire 5 ' addresDM [4:0] $end
$var wire 1 $ clk $end
$var wire 32 ( wd [31:0] $end
$var wire 1 & we $end
$var reg 32 ) rd [31:0] $end
$upscope $end
$upscope $end
$enddefinitions $end
$comment Show the parameter values. $end
$dumpall
b1010 "
$end
#0
$dumpvars
bx )
b10100101101001011010010110100101 (
b0 '
1&
b10100101101001011010010110100101 %
0$
b0 #
bx !
$end
#50000
1$
#100000
0$
b11111111111111110000111111111111 %
b11111111111111110000111111111111 (
0&
#150000
b10100101101001011010010110100101 !
b10100101101001011010010110100101 )
1$
#200000
0$
1&
b11011110101011011011111011101111 %
b11011110101011011011111011101111 (
b1 #
b1 '
#250000
bx !
bx )
1$
#300000
0$
#350000
b11011110101011011011111011101111 !
b11011110101011011011111011101111 )
1$
#400000
0$
b11111111111111111111111111111111 %
b11111111111111111111111111111111 (
b10 #
b10 '
#450000
bx !
bx )
1$
#500000
0$
#550000
b11111111111111111111111111111111 !
b11111111111111111111111111111111 )
1$
#600000
0$
b10010001101000101011001111000 %
b10010001101000101011001111000 (
b11 #
b11 '
#650000
bx !
bx )
1$
#700000
0$
#750000
b10010001101000101011001111000 !
b10010001101000101011001111000 )
1$
