Contador de programa/PC.v
module PC(
    input clk,                  // Reloj
    input [31:0] pcNext,        // Entrada de datos
    output reg [31:0] pc        // Salida del registro
);
    initial pc = 32'd0;


    // Bloque secuencial para actualizar el registro
    always @(posedge clk) begin
        pc = pcNext;
    end
endmodule

Contador de programa/PC_tb.v
`default_nettype none
`define DUMPSTR(x) `"x.vcd`"
`timescale 100 ns / 10 ns

module PC_tb();

parameter DURATION = 10;

reg clk = 0;
always #0.5 clk = ~clk;

reg [31:0] pcNext_tb;           //PCNEXT            
wire [31:0] pc_tb;              //PC

PC UUT (
    .pcNext(pcNext_tb),
    .pc(pc_tb),
    .clk(clk)
);

initial begin

    $dumpfile(`DUMPSTR(`VCD_OUTPUT));
    $dumpvars(0, PC_tb);

    pcNext_tb = 32'd0;
    #1;
    pcNext_tb = 32'd1;
    #1;
    pcNext_tb = 32'd5;
    #1;
    pcNext_tb = 32'd9;
    #1;
    pcNext_tb = 32'd10;
    #1;
    pcNext_tb = 32'd1;
    #1;


    #(DURATION) $display("End of simulation");
    $finish;
end

endmodule

Contador de programa/PC_tb.vcd
$date
	Sat Nov 16 21:32:47 2024
$end
$version
	Icarus Verilog
$end
$timescale
	1ps
$end
$scope module PC_tb $end
$var wire 32 ! pc_tb [31:0] $end
$var parameter 32 " DURATION $end
$var reg 1 # clk $end
$var reg 32 $ pcNext_tb [31:0] $end
$scope module UUT $end
$var wire 1 # clk $end
$var wire 32 % pcNext [31:0] $end
$var reg 32 & pc [31:0] $end
$upscope $end
$upscope $end
$enddefinitions $end
$comment Show the parameter values. $end
$dumpall
b1010 "
$end
#0
$dumpvars
b0 &
b0 %
b0 $
0#
b0 !
$end
#50000
1#
#100000
0#
b1 $
b1 %
#150000
b1 !
b1 &
1#
#200000
0#
b101 $
b101 %
#250000
b101 !
b101 &
1#
#300000
0#
b1001 $
b1001 %
#350000
b1001 !
b1001 &
1#
#400000
0#
b1010 $
b1010 %
#450000
b1010 !
b1010 &
1#
#500000
0#
b1 $
b1 %
#550000
b1 !
b1 &
1#
