Unidad Aritmetico Logica/ALU.v
module ALU(
    input signed [31:0] srcA,           // Operando A
    input signed [31:0] srcB,           // Operando B
    input [2:0] ALUControl,             // Código de operación
    output reg [31:0] result,           // Resultado de la operación
    output reg zero                     // Señal si el resultado es 0
);

always @(*) begin
    case(ALUControl)
        3'b000: result = srcA + srcB;                       // Suma
        3'b001: result = srcA - srcB;                       // Resta 
        3'b010: result = srcA & srcB;                       // AND
        3'b011: result = srcA | srcB;                       // OR
        3'b101: result = (srcA < srcB) ? 32'b1 : 32'b0;     // Set Less Than (SLT)
        default: result = 32'b0;                            // Valor por defecto
    endcase
    zero = (result == 1'b0) ? 1'b1 : 1'b0;                  //Señal si el resutado de 0

end

endmodule

Unidad Aritmetico Logica/ALU_tb.v
`default_nettype none
`define DUMPSTR(x) `"x.vcd`"
`timescale 1 ns / 1 ps

module ALU_tb();

    reg signed [31:0] srcA_tb, srcB_tb;     // Entradas de 32 bits
    reg [2:0] ALUControl_tb;                // Código de control de la ALU
    wire [31:0] result_tb;                  // Salida de 32 bits
    wire zero_tb;
    ALU UUT (
        .srcA(srcA_tb),
        .srcB(srcB_tb),
        .ALUControl(ALUControl_tb),
        .result(result_tb),
        .zero(zero_tb)
    );

    initial begin
        $dumpfile(`DUMPSTR(`VCD_OUTPUT));
        $dumpvars(0, ALU_tb);

        // Prueba de suma
        srcA_tb = 32'd15;
        srcB_tb = 32'd10;
        ALUControl_tb = 3'b000;
        #1;

        // Prueba de suma con negativos
        srcA_tb = -32'd15;
        srcB_tb = 32'd10;
        ALUControl_tb = 3'b000;
        #1;

        // Prueba de resta
        srcA_tb = 32'd20;
        srcB_tb = 32'd5;
        ALUControl_tb = 3'b001;
        #1;

        // Prueba de resta con negativos
        srcA_tb = 32'd20;
        srcB_tb = -32'd5;
        ALUControl_tb = 3'b001;
        #1;

        // Prueba de AND
        srcA_tb = 32'h0F0F0F0F;
        srcB_tb = 32'h00FF00FF;
        ALUControl_tb = 3'b010;
        #1;
       
        // Prueba de OR
        srcA_tb = 32'h0F0F0F0F;
        srcB_tb = 32'h00FF00FF;
        ALUControl_tb = 3'b011;
        #1;
       
        // Prueba de SLT (Set Less Than)
        srcA_tb = 32'd5;
        srcB_tb = 32'd10;
        ALUControl_tb = 3'b101;
        #1;

        // Prueba de SLT (Set Less Than) con negativos
        srcA_tb = 32'd5;
        srcB_tb = -32'd10;
        ALUControl_tb = 3'b101;
        #1;


        $display("End of simulation");
        $finish;
    end

endmodule

Unidad Aritmetico Logica/ALU_tb.vcd
$date
	Sun Nov 17 00:51:01 2024
$end
$version
	Icarus Verilog
$end
$timescale
	1ps
$end
$scope module ALU_tb $end
$var wire 1 ! zero_tb $end
$var wire 32 " result_tb [31:0] $end
$var reg 3 # ALUControl_tb [2:0] $end
$var reg 32 $ srcA_tb [31:0] $end
$var reg 32 % srcB_tb [31:0] $end
$scope module UUT $end
$var wire 3 & ALUControl [2:0] $end
$var wire 32 ' srcA [31:0] $end
$var wire 32 ( srcB [31:0] $end
$var reg 32 ) result [31:0] $end
$var reg 1 ! zero $end
$upscope $end
$upscope $end
$enddefinitions $end
$comment Show the parameter values. $end
$dumpall
$end
#0
$dumpvars
b11001 )
b1010 (
b1111 '
b0 &
b1010 %
b1111 $
b0 #
b11001 "
0!
$end
#1000
b11111111111111111111111111111011 "
b11111111111111111111111111111011 )
b11111111111111111111111111110001 $
b11111111111111111111111111110001 '
#2000
b1111 "
b1111 )
b1 #
b1 &
b101 %
b101 (
b10100 $
b10100 '
#3000
b11001 "
b11001 )
b11111111111111111111111111111011 %
b11111111111111111111111111111011 (
#4000
b11110000000000001111 "
b11110000000000001111 )
b10 #
b10 &
b111111110000000011111111 %
b111111110000000011111111 (
b1111000011110000111100001111 $
b1111000011110000111100001111 '
#5000
b1111111111110000111111111111 "
b1111111111110000111111111111 )
b11 #
b11 &
#6000
b1 "
b1 )
b101 #
b101 &
b1010 %
b1010 (
b101 $
b101 '
#7000
1!
b0 "
b0 )
b11111111111111111111111111110110 %
b11111111111111111111111111110110 (
