Memoria de Instrucciones/IM.v
module  IM(
    input [4:0] addresIM,       // Entrada de direccion del dato
    output wire [31:0] inst     // Salida del dato
);
    reg [31:0] memoria_de_instricciones [0:31];

    //Instrucciones
    initial begin
        $readmemh("../instrucciones.hex", memoria_de_instricciones);
    end

assign inst = memoria_de_instricciones[addresIM];

endmodule

Memoria de Instrucciones/IM_tb.v
`default_nettype none
`define DUMPSTR(x) `"x.vcd`"
`timescale 100 ns / 10 ns

module IM_tb();

parameter DURATION = 10;

reg clk = 0;
always #0.5 clk = ~clk;

reg [31:0] addres;
wire [31:0] instruccion;

IM UUT (
    .addresIM(addres[6:2]),
    .inst(instruccion)
);

integer i;

initial begin

    $dumpfile(`DUMPSTR(`VCD_OUTPUT));
    $dumpvars(0, IM_tb);

    for (i = 0; i < 32; i = i + 4) begin
        #1        
            addres = i;
    end

    #(DURATION) $display("End of simulation");
    $finish;
end

endmodule

Memoria de Instrucciones/IM_tb.vcd
$date
	Mon Nov 25 03:05:11 2024
$end
$version
	Icarus Verilog
$end
$timescale
	1ps
$end
$scope module IM_tb $end
$var wire 32 ! instruccion [31:0] $end
$var parameter 32 " DURATION $end
$var reg 32 # addres [31:0] $end
$var reg 1 $ clk $end
$var integer 32 % i [31:0] $end
$scope module UUT $end
$var wire 5 & addresIM [4:0] $end
$var wire 32 ' inst [31:0] $end
$upscope $end
$upscope $end
$enddefinitions $end
$comment Show the parameter values. $end
$dumpall
b1010 "
$end
#0
$dumpvars
bx '
bx &
b0 %
0$
bx #
bx !
$end
#50000
1$
#100000
b1100000000010000010011 !
b1100000000010000010011 '
b0 &
0$
b100 %
b0 #
#150000
1$
#200000
b100000000010010010011 !
b100000000010010010011 '
b1 &
0$
b1000 %
b100 #
#250000
1$
#300000
b1000000000000100100010011 !
b1000000000000100100010011 '
b10 &
0$
b1100 %
b1000 #
#350000
1$
#400000
b100101000110001010110011 !
b100101000110001010110011 '
b11 &
0$
b10000 %
b1100 #
#450000
1$
#500000
b100101000111001100110011 !
b100101000111001100110011 '
b100 &
0$
b10100 %
b10000 #
#550000
1$
#600000
b100101000000001110110011 !
b100101000000001110110011 '
b101 &
0$
b11000 %
b10100 #
#650000
1$
#700000
b1000000100101000000111000110011 !
b1000000100101000000111000110011 '
b110 &
0$
b11100 %
b11000 #
#750000
1$
#800000
b1000000100001001000111010110011 !
b1000000100001001000111010110011 '
b111 &
0$
b100000 %
b11100 #
#850000
1$
#900000
b100101000010111100110011 !
b100101000010111100110011 '
b1000 &
0$
b100100 %
b100000 #
#950000
1$
#1000000
b100001001010111110110011 !
b100001001010111110110011 '
b1001 &
0$
b101000 %
b100100 #
#1050000
1$
#1100000
b1110101001010111110110011 !
b1110101001010111110110011 '
b1010 &
0$
b101100 %
b101000 #
#1150000
1$
#1200000
b100000000001010010011 !
b100000000001010010011 '
b1011 &
0$
b110000 %
b101100 #
#1250000
1$
#1300000
b1100010011 !
b1100010011 '
b1100 &
0$
b110100 %
b110000 #
#1350000
1$
#1400000
b1001000101000100001100011 !
b1001000101000100001100011 '
b1101 &
0$
b111000 %
b110100 #
#1450000
1$
#1500000
b10100101000001010110011 !
b10100101000001010110011 '
b1110 &
0$
b111100 %
b111000 #
#1550000
1$
#1600000
b100110000001100010011 !
b100110000001100010011 '
b1111 &
0$
b1000000 %
b111100 #
#1650000
1$
#1700000
b11111111010111111111000001101111 !
b11111111010111111111000001101111 '
b10000 &
0$
b1000100 %
b1000000 #
#1750000
1$
#1800000
b10010110011 !
b10010110011 '
b10001 &
0$
b1001000 %
b1000100 #
#1850000
1$
#1900000
b1010010011 !
b1010010011 '
b10010 &
0$
b1001100 %
b1001000 #
#1950000
1$
#2000000
b101000000000001100010011 !
b101000000000001100010011 '
b10011 &
0$
b1010000 %
b1001100 #
#2050000
1$
#2100000
b11000101000100001100011 !
b11000101000100001100011 '
b10100 &
0$
b1010100 %
b1010000 #
#2150000
1$
#2200000
b100001001000010010110011 !
b100001001000010010110011 '
b10101 &
0$
b1011000 %
b1010100 #
#2250000
1$
#2300000
b100101000001010010011 !
b100101000001010010011 '
b10110 &
0$
b1011100 %
b1011000 #
#2350000
1$
#2400000
b11111111010111111111000001101111 !
b11111111010111111111000001101111 '
b10111 &
0$
b1100000 %
b1011100 #
#2450000
1$
#2500000
b100000000010000000100011 !
b100000000010000000100011 '
b11000 &
0$
b1100100 %
b1100000 #
#2550000
1$
#2600000
b100100000010001000100011 !
b100100000010001000100011 '
b11001 &
0$
b1101000 %
b1100100 #
#2650000
1$
#2700000
b1001000000010010000100011 !
b1001000000010010000100011 '
b11010 &
0$
b1101100 %
b1101000 #
#2750000
1$
#2800000
b10001010000011 !
b10001010000011 '
b11011 &
0$
b1110000 %
b1101100 #
#2850000
1$
#2900000
b10000000010001100000011 !
b10000000010001100000011 '
b11100 &
0$
b1110100 %
b1110000 #
#2950000
1$
#3000000
b100000000010001110000011 !
b100000000010001110000011 '
b11101 &
0$
b1111000 %
b1110100 #
#3050000
1$
#3100000
bx !
bx '
b11110 &
0$
b1111100 %
b1111000 #
#3150000
1$
#3200000
b11111 &
0$
b10000000 %
b1111100 #
