Memoria de Instrucciones/IM.v
module  IM(
    input [4:0] addresIM,       // Entrada de direccion del dato
    output wire [31:0] inst     // Salida del dato
);
    reg [31:0] memoria_de_instricciones [0:31];

    //Instrucciones
    initial begin
        memoria_de_instricciones[0] = 32'h00300413;
        memoria_de_instricciones[1] = 32'h00100493;
        memoria_de_instricciones[2] = 32'h01000913;
        memoria_de_instricciones[3] = 32'h009462b3;
        memoria_de_instricciones[4] = 32'h00947333;
        memoria_de_instricciones[5] = 32'h009403b3;
        memoria_de_instricciones[6] = 32'h40940e33;
        memoria_de_instricciones[7] = 32'h40848eb3;
        memoria_de_instricciones[8] = 32'h00942f33;
        memoria_de_instricciones[9] = 32'h0084afb3;
        memoria_de_instricciones[10] = 32'h01d4afb3;
        memoria_de_instricciones[11] = 32'h00100293;
        memoria_de_instricciones[12] = 32'h00000313;
        memoria_de_instricciones[13] = 32'h01228863;
        memoria_de_instricciones[14] = 32'h005282b3;
        memoria_de_instricciones[15] = 32'h00130313;
        memoria_de_instricciones[16] = 32'hff5ff06f;
        memoria_de_instricciones[17] = 32'h000004b3;
        memoria_de_instricciones[18] = 32'h00000293;
        memoria_de_instricciones[19] = 32'h00a00313;
        memoria_de_instricciones[20] = 32'h00628863;
        memoria_de_instricciones[21] = 32'h008484b3;
        memoria_de_instricciones[22] = 32'h00128293;
        memoria_de_instricciones[23] = 32'hff5ff06f;
        memoria_de_instricciones[24] = 32'h00802023;
        memoria_de_instricciones[25] = 32'h00902223;
        memoria_de_instricciones[26] = 32'h01202423;
        memoria_de_instricciones[27] = 32'h00002283;
        memoria_de_instricciones[28] = 32'h00402303;
        memoria_de_instricciones[29] = 32'h00802383;
    end

assign inst = memoria_de_instricciones[addresIM];

endmodule

Memoria de Instrucciones/IM_tb.v
`default_nettype none
`define DUMPSTR(x) `"x.vcd`"
`timescale 100 ns / 10 ns

module IM_tb();

parameter DURATION = 10;

reg clk = 0;
always #0.5 clk = ~clk;

reg [31:0] addres;
wire [31:0] instruccion;

IM UUT (
    .addresIM(addres[6:2]),
    .inst(instruccion)
);

integer i;

initial begin

    $dumpfile(`DUMPSTR(`VCD_OUTPUT));
    $dumpvars(0, IM_tb);

    for (i = 0; i < 32; i = i + 4) begin
        #1        
            addres = i;
    end

    #(DURATION) $display("End of simulation");
    $finish;
end

endmodule

Memoria de Instrucciones/IM_tb.vcd
$date
	Wed Nov 06 00:45:24 2024
$end
$version
	Icarus Verilog
$end
$timescale
	1ps
$end
$scope module IM_tb $end
$var wire 32 ! instruccion [31:0] $end
$var parameter 32 " DURATION $end
$var reg 32 # addres [31:0] $end
$var reg 1 $ clk $end
$var integer 32 % i [31:0] $end
$scope module UUT $end
$var wire 5 & addresIM [4:0] $end
$var wire 32 ' inst [31:0] $end
$upscope $end
$upscope $end
$enddefinitions $end
$comment Show the parameter values. $end
$dumpall
b1010 "
$end
#0
$dumpvars
bx '
bx &
b0 %
0$
bx #
bx !
$end
#50000
1$
#100000
b1100000000010000010011 !
b1100000000010000010011 '
b0 &
0$
b100 %
b0 #
#150000
1$
#200000
b100000000010010010011 !
b100000000010010010011 '
b1 &
0$
b1000 %
b100 #
#250000
1$
#300000
b1000000000000100100010011 !
b1000000000000100100010011 '
b10 &
0$
b1100 %
b1000 #
#350000
1$
#400000
b100101000110001010110011 !
b100101000110001010110011 '
b11 &
0$
b10000 %
b1100 #
#450000
1$
#500000
b100101000111001100110011 !
b100101000111001100110011 '
b100 &
0$
b10100 %
b10000 #
#550000
1$
#600000
b100101000000001110110011 !
b100101000000001110110011 '
b101 &
0$
b11000 %
b10100 #
#650000
1$
#700000
b1000000100101000000111000110011 !
b1000000100101000000111000110011 '
b110 &
0$
b11100 %
b11000 #
#750000
1$
#800000
b1000000100001001000111010110011 !
b1000000100001001000111010110011 '
b111 &
0$
b100000 %
b11100 #
